minilop/__init__.py
minilop/amqp/__init__.py
minilop/amqp/components.py
minilop/amqp/connections.py
minilop/amqp/exceptions.py
minilop-0.1.9.dist-info/WHEEL
minilop-0.1.9.dist-info/METADATA
minilop-0.1.9.dist-info/RECORD
